PYREADME.md
gdsfactoryplus/__init__.py
gdsfactoryplus/__init__.pyi
gdsfactoryplus/cli_test.py
gdsfactoryplus/gdsfactoryplus.cp312-win_amd64.pyd
gdsfactoryplus/gdsfactoryplus.pyi
gdsfactoryplus/generate_svg.py
gdsfactoryplus/logger.py
gdsfactoryplus/models.py
gdsfactoryplus/project.py
gdsfactoryplus/registry.py
gdsfactoryplus/settings.py
gdsfactoryplus/show.py
gdsfactoryplus/sim.py
gdsfactoryplus/simulate.py
gdsfactoryplus/version.py
gdsfactoryplus/assets/_svg/_empty.svg
gdsfactoryplus/assets/_svg/_exploded.svg
gdsfactoryplus/assets/_svg/_port.svg
gdsfactoryplus/assets/css/scm.css
gdsfactoryplus/assets/fonts/FiraMono-Bold.ttf
gdsfactoryplus/assets/fonts/FiraSans-Bold.ttf
gdsfactoryplus/assets/fonts/OFL.txt
gdsfactoryplus/assets/js/.gitignore
gdsfactoryplus/assets/js/override.example.js
gdsfactoryplus/assets/js/scm.js
gdsfactoryplus/assets/js/view.js
gdsfactoryplus/assets/json/base_schema.json
gdsfactoryplus/assets/shaders/rounded_box.wgsl
gdsfactoryplus/cli/__init__.py
gdsfactoryplus/cli/app.py
gdsfactoryplus/cli/check.py
gdsfactoryplus/cli/cli_test.py
gdsfactoryplus/cli/configure.py
gdsfactoryplus/cli/export_spice.py
gdsfactoryplus/cli/parse_spice.py
gdsfactoryplus/cli/serve.py
gdsfactoryplus/cli/settings.py
gdsfactoryplus/cli/version.py
gdsfactoryplus/cli/watch.py
gdsfactoryplus/core/__init__.py
gdsfactoryplus/core/__init__.pyi
gdsfactoryplus/core/bbox.cp314-win_amd64.pyd
gdsfactoryplus/core/build.cp314-win_amd64.pyd
gdsfactoryplus/core/callgraph.cp314-win_amd64.pyd
gdsfactoryplus/core/check.cp314-win_amd64.pyd
gdsfactoryplus/core/communication.cp314-win_amd64.pyd
gdsfactoryplus/core/database.cp314-win_amd64.pyd
gdsfactoryplus/core/export_spice.cp314-win_amd64.pyd
gdsfactoryplus/core/freeze.cp314-win_amd64.pyd
gdsfactoryplus/core/get_netlist.cp314-win_amd64.pyd
gdsfactoryplus/core/gfp_vlsir.cp314-win_amd64.pyd
gdsfactoryplus/core/imports.cp314-win_amd64.pyd
gdsfactoryplus/core/initialize.cp314-win_amd64.pyd
gdsfactoryplus/core/kcl.cp314-win_amd64.pyd
gdsfactoryplus-1.3.13.dist-info/METADATA
gdsfactoryplus-1.3.13.dist-info/WHEEL
gdsfactoryplus-1.3.13.dist-info/entry_points.txt
gdsfactoryplus-1.3.13.dist-info/RECORD
