Metadata-Version: 2.1
Name: gdsfactoryplus
Version: 1.3.13
Summary: GDSFactory+: adds powerful features such as foundry PDKs, simulations, and verification tools like DRC and LVS.
Author: GDSFactory
Author-Email: contact@gdsfactory.com
License: PROPRIETARY AND CONFIDENTIAL
Requires-Python: >=3.12
Classifier: Intended Audience :: Science/Research
Classifier: Operating System :: OS Independent
Classifier: Programming Language :: Python :: 3.12
Classifier: Programming Language :: Python :: 3.13
Classifier: Programming Language :: Python :: 3.14
Classifier: Topic :: Scientific/Engineering
Classifier: Topic :: Scientific/Engineering :: Physics
Keywords: eda,photonics,python,drc,verification,lvs,simulation
Requires-Dist: altair>=5.0.0
Requires-Dist: bokeh>=3.6.0
Requires-Dist: cookiecutter>=2.0.0
Requires-Dist: deepdiff>=8.0.0
Requires-Dist: doroutes>=0.0.2
Requires-Dist: frozendict>=2.4.6
Requires-Dist: doweb>=1.7.1
Requires-Dist: gdsfactory>=8.0.0
Requires-Dist: granian>=2.2.5
Requires-Dist: gunicorn>=23.0.0
Requires-Dist: httpx>=0.28.0
Requires-Dist: jax>=0.5.0
Requires-Dist: kfactory>=1.7.1
Requires-Dist: klujax>=0.4.1
Requires-Dist: lazy-loader>=0.4
Requires-Dist: networkx>=3.5
Requires-Dist: numpy>=2.0.0
Requires-Dist: orjson>=3.10.16
Requires-Dist: packaging>=24.2
Requires-Dist: pip-system-certs>=5.2
Requires-Dist: pyarrow>=21.0.0
Requires-Dist: pydantic>=2.11.0
Requires-Dist: pydantic-settings>=2.8.1
Requires-Dist: pydot>=4.0.1
Requires-Dist: pytest>=8.3.5
Requires-Dist: rich>=13.0.0
Requires-Dist: sax>=0.15.19
Requires-Dist: toml>=0.10.0
Requires-Dist: tqdm>=4.67.1
Requires-Dist: trimesh[easy]>=4.6.6
Requires-Dist: typer>=0.15.4
Requires-Dist: typing-extensions>=4.13.2
Requires-Dist: vlsir>=7.0.0
Requires-Dist: vlsirtools>=7.0.0
Requires-Dist: websocket-client>=1.8.0
